pygrain/__init__.py
pygrain/app.py
pygrain/box.py
pygrain/button.py
pygrain/component.py
pygrain/events.py
pygrain/frame.py
pygrain/horizontal_scroll_bar.py
pygrain/image.py
pygrain/point.py
pygrain/scroll_bar.py
pygrain/textbox.py
pygrain/tkinter_window.py
pygrain/toggle_switch.py
pygrain/util.py
pygrain/value_slider.py
pygrain/vertical_scroll_bar.py
pygrain-0.4.2.dist-info/LICENSE
pygrain-0.4.2.dist-info/METADATA
pygrain-0.4.2.dist-info/WHEEL
pygrain-0.4.2.dist-info/top_level.txt
pygrain-0.4.2.dist-info/RECORD
