Metadata-Version: 2.1
Name: pygrain
Version: 0.4.2
Summary: Application development framework built using pygame with tkinter integration
Home-page: https://github.com/RohanAnandPandit/pygrain
Author: Rohan Pandit
Author-email: rohananandpandit@gmail.com
License: UNKNOWN
Project-URL: Bug Tracker, https://github.com/pypa/sampleproject/issues
Platform: UNKNOWN
Classifier: Programming Language :: Python :: 3
Classifier: License :: OSI Approved :: MIT License
Classifier: Operating System :: OS Independent
Requires-Python: >=3.6
License-File: LICENSE
Requires-Dist: pygame
